Workbook

Sheet TOC
A1: 11222B3
B2: Table of Contents
B3: 1 | C3: 'Overview'!A1
B4: 2 | C4: 'VLOOKUP Definition'!A1
B5: 3 | C5: 'VLOOKUP Uses'!A1
B6: 4 | C6: 'Write a VLOOKUP'!A1
B7: 5 | C7: 'Errors'!A1
B8: 6 | C8: 'First Match & Sorting'!A1
B9: 7 | C9: 'Relationships'!A1
B10: 8 | C10: 'Lookup Tables'!A1
C12: This Table of Contents was created in
C13: one click with the Tab Hound Add-in.

Sheet VLOOKUP Definition

Sheet VLOOKUP Uses
A1: What can we use VLOOKUP for?
B3: Create Relationships Between Data & Lookup Tables
B24: Search Tables & Databases
B46: Interactive Reports & Financial Models
B68: Tax & Commission Rate Calculations

Sheet Write a VLOOKUP
A1: How to Write a VLOOKUP Formula
A3: CLASSIC FAVORITES | B3: TALL | C3: GRANDE | D3: VENTI
A4: Caffe Latte | B4: 2.95 | C4: 3.75 | D4: 4.15
A5: Cappuccino | B5: 2.95 | C5: 3.65 | D5: 4.15
A6: Caramel Macchiato | B6: 3.75 | C6: 3.95 | D6: 4.25
A7: Caffe Mocha | B7: 3.25 | C7: 3.95 | D7: 4.4
A8: White Chocolate Mocha | B8: 3.45 | C8: 4.15 | D8: 4.55
A9: Caffe Americano | B9: 2 | C9: 2.4 | D9: 2.75
A10: Cinnamon Dolce Latte | B10: 3.95 | C10: 4.75 | D10: 5.15
A11: Drip Coffee | B11: 1.75 | C11: 1.95 | D11: 2.05
A13: Question: What is the price of a Caffe Mocha, size Grande?
A15: Caffe Mocha | B15: =VLOOKUP(A15,$A$4:$D$11,3,0) -> 3.95

Sheet Errors
A1: The Two Main Causes of Errors
A3: CLASSIC FAVORITES | B3: TALL | C3: GRANDE | D3: VENTI
A4: Caffe Latte | B4: 2.95 | C4: 3.75 | D4: 4.15
A5: Cappuccino | B5: 2.95 | C5: 3.65 | D5: 4.15
A6: Caramel Macchiato | B6: 3.75 | C6: 3.95 | D6: 4.25
A7: Caffe Mocha | B7: 3.25 | C7: 3.95 | D7: 4.4
A8: White Chocolate Mocha | B8: 3.45 | C8: 4.15 | D8: 4.55
A9: Caffe Americano | B9: 2 | C9: 2.4 | D9: 2.75
A10: Cinnamon Dolce Latte | B10: 3.95 | C10: 4.75 | D10: 5.15
A11: Drip Coffee | B11: 1.75 | C11: 1.95 | D11: 2.05
A13: Question: How much will this order cost for size Grandes?
B15: Grande
A16: White Chocolate Mocha | B16: =VLOOKUP(A16,$A$4:$D$11,3,0) -> 4.15
A17: Caffe Latte | B17: =VLOOKUP(A17,$A$4:$D$11,3,0) -> 3.75
A18: Caramel Macchiato | B18: =VLOOKUP(A18,$A$4:$D$11,3,0) -> 3.95
A19: Caffe Mocha | B19: =VLOOKUP(A19,$A$4:$D$11,3,0) -> 3.95 | D19: h
A20: Total | B20: =SUM(B16:B19) -> 15.8

Sheet First Match & Sorting
A1: Stops at First Match & Sorting Data
A3: CLASSIC FAVORITES | B3: TALL | C3: GRANDE | D3: VENTI
A4: Caffe Latte | B4: 2.95 | C4: 3.75 | D4: 4.15
A5: Cappuccino | B5: 2.95 | C5: 3.65 | D5: 4.15
A6: White Chocolate Mocha | B6: 3.45 | C6: 4.15 | D6: 4.55
A7: Caffe Mocha | B7: 3.25 | C7: 3.95 | D7: 4.4
A8: Caramel Macchiato | B8: 3.75 | C8: 3.95 | D8: 4.25
A9: Caffe Mocha | B9: 2.25 | C9: 2.5 | D9: 2.75
A10: Cinnamon Dolce Latte | B10: 3.95 | C10: 4.75 | D10: 5.15
A11: Steamer | B11: 2.25 | C11: 2.5 | D11: 2.75
A12: Drip Coffee | B12: 1.75 | C12: 1.95 | D12: 2.05
A14: Question: What is the price of a Caffe Mocha, size Grande?
A16: Caffe Mocha | B16: =VLOOKUP(A16,A4:D12,3,0) -> 3.95

Sheet Relationships
A1: Create Relationships Between Tables - VLOOKUP to Other Sheets
A3: Order ID | B3: Customer ID | C3: Salesperson | D3: Product Name | E3: Revenue | F3: Product Category | G3: Rep's Region
A4: 1001 | B4: 27 | C4: Mariya Sergienko | D4: Wine | E4: 686 | F4: =VLOOKUP(Relationships!D4,'Lookup Tables'!$A$4:$B$20,2,0) -> Beverages | G4: =VLOOKUP(C4,'Lookup Tables'!$E$4:$K$11,7,0) -> West
A5: 1002 | B5: 27 | C5: Mariya Sergienko | D5: Dried Plums | E5: 164.5 | F5: =VLOOKUP(Relationships!D5,'Lookup Tables'!$A$4:$B$20,2,0) -> Dried Fruit & Nuts | G5: =VLOOKUP(C5,'Lookup Tables'!$E$4:$K$11,7,0) -> West
A6: 1003 | B6: 4 | C6: Andrew Cencini | D6: Dried Pears | E6: 2070 | F6: =VLOOKUP(Relationships!D6,'Lookup Tables'!$A$4:$B$20,2,0) -> Dried Fruit & Nuts | G6: =VLOOKUP(C6,'Lookup Tables'!$E$4:$K$11,7,0) -> East
A7: 1004 | B7: 4 | C7: Andrew Cencini | D7: Dried Apples | E7: 4717 | F7: =VLOOKUP(Relationships!D7,'Lookup Tables'!$A$4:$B$20,2,0) -> Dried Fruit & Nuts | G7: =VLOOKUP(C7,'Lookup Tables'!$E$4:$K$11,7,0) -> East
A8: 1005 | B8: 4 | C8: Andrew Cencini | D8: Dried Plums | E8: 38.5 | F8: =VLOOKUP(Relationships!D8,'Lookup Tables'!$A$4:$B$20,2,0) -> Dried Fruit & Nuts | G8: =VLOOKUP(C8,'Lookup Tables'!$E$4:$K$11,7,0) -> East
A9: 1006 | B9: 12 | C9: Mariya Sergienko | D9: Chai | E9: 1458 | F9: =VLOOKUP(Relationships!D9,'Lookup Tables'!$A$4:$B$20,2,0) -> Beverages | G9: =VLOOKUP(C9,'Lookup Tables'!$E$4:$K$11,7,0) -> West
A10: 1007 | B10: 12 | C10: Mariya Sergienko | D10: Coffee | E10: 2024 | F10: =VLOOKUP(Relationships!D10,'Lookup Tables'!$A$4:$B$20,2,0) -> Beverages | G10: =VLOOKUP(C10,'Lookup Tables'!$E$4:$K$11,7,0) -> West
A11: 1008 | B11: 8 | C11: Nancy Freehafer | D11: Chocolate Biscuits Mix | E11: 349.6 | F11: =VLOOKUP(Relationships!D11,'Lookup Tables'!$A$4:$B$20,2,0) -> Baked Goods & Mixes | G11: =VLOOKUP(C11,'Lookup Tables'!$E$4:$K$11,7,0) -> North
A12: 1009 | B12: 4 | C12: Andrew Cencini | D12: Chocolate Biscuits Mix | E12: 809.6 | F12: =VLOOKUP(Relationships!D12,'Lookup Tables'!$A$4:$B$20,2,0) -> Baked Goods & Mixes | G12: =VLOOKUP(C12,'Lookup Tables'!$E$4:$K$11,7,0) -> East
A13: 1010 | B13: 29 | C13: Jan Kotas | D13: Chocolate | E13: 1198.5 | F13: =VLOOKUP(Relationships!D13,'Lookup Tables'!$A$4:$B$20,2,0) -> Candy | G13: =VLOOKUP(C13,'Lookup Tables'!$E$4:$K$11,7,0) -> West
A14: 1011 | B14: 3 | C14: Mariya Sergienko | D14: Clam Chowder | E14: 878.15 | F14: =VLOOKUP(Relationships!D14,'Lookup Tables'!$A$4:$B$20,2,0) -> Soups | G14: =VLOOKUP(C14,'Lookup Tables'!$E$4:$K$11,7,0) -> West
A15: 1012 | B15: 6 | C15: Michael Neipper | D15: Curry Sauce | E15: 1280 | F15: =VLOOKUP(Relationships!D15,'Lookup Tables'!$A$4:$B$20,2,0) -> Sauces | G15: =VLOOKUP(C15,'Lookup Tables'!$E$4:$K$11,7,0) -> North
... A34: 1032 | B34: 3 | C34: Mariya Sergienko | D34: Curry Sauce | E34: 1200 | F34: =VLOOKUP(Relationships!D34,'Lookup Tables'!$A$4:$B$20,2,0) -> Sauces | G34: =VLOOKUP(C34,'Lookup Tables'!$E$4:$K$11,7,0) -> West
A35: 1033 | B35: 6 | C35: Michael Neipper | E35: 1 | F35: =VLOOKUP(Relationships!D35,'Lookup Tables'!$A$4:$B$20,2,0) -> #N/A | G35: =VLOOKUP(C35,'Lookup Tables'!$E$4:$K$11,7,0) -> North
A36: 1034 | B36: 28 | C36: Anne Larsen | E36: 1 | F36: =VLOOKUP(Relationships!D36,'Lookup Tables'!$A$4:$B$20,2,0) -> #N/A | G36: =VLOOKUP(C36,'Lookup Tables'!$E$4:$K$11,7,0) -> South
A37: 1035 | B37: 8 | C37: Nancy Freehafer | E37: 1 | F37: =VLOOKUP(Relationships!D37,'Lookup Tables'!$A$4:$B$20,2,0) -> #N/A | G37: =VLOOKUP(C37,'Lookup Tables'!$E$4:$K$11,7,0) -> North
A38: 1036 | B38: 10 | C38: Laura Giussani | D38: Cajun Seasoning | E38: 470 | F38: =VLOOKUP(Relationships!D38,'Lookup Tables'!$A$4:$B$20,2,0) -> Condiments | G38: =VLOOKUP(C38,'Lookup Tables'!$E$4:$K$11,7,0) -> East
A39: 1038 | B39: 10 | C39: Laura Giussani | D39: Dried Plums | E39: 171.5 | F39: =VLOOKUP(Relationships!D39,'Lookup Tables'!$A$4:$B$20,2,0) -> Dried Fruit & Nuts | G39: =VLOOKUP(C39,'Lookup Tables'!$E$4:$K$11,7,0) -> East
A40: 1039 | B40: 11 | C40: Anne Larsen | D40: Curry Sauce | E40: 2880 | F40: =VLOOKUP(Relationships!D40,'Lookup Tables'!$A$4:$B$20,2,0) -> Sauces | G40: =VLOOKUP(C40,'Lookup Tables'!$E$4:$K$11,7,0) -> South
A41: 1040 | B41: 1 | C41: Nancy Freehafer | D41: Crab Meat | E41: 239.2 | F41: =VLOOKUP(Relationships!D41,'Lookup Tables'!$A$4:$B$20,2,0) -> Canned Meat | G41: =VLOOKUP(C41,'Lookup Tables'!$E$4:$K$11,7,0) -> North
A42: 1041 | B42: 28 | C42: Anne Larsen | D42: Coffee | E42: 1472 | F42: =VLOOKUP(Relationships!D42,'Lookup Tables'!$A$4:$B$20,2,0) -> Beverages | G42: =VLOOKUP(C42,'Lookup Tables'!$E$4:$K$11,7,0) -> South
A43: 1042 | B43: 9 | C43: Robert Zare | D43: Clam Chowder | E43: 260.55 | F43: =VLOOKUP(Relationships!D43,'Lookup Tables'!$A$4:$B$20,2,0) -> Soups | G43: =VLOOKUP(C43,'Lookup Tables'!$E$4:$K$11,7,0) -> West
A44: 1043 | B44: 6 | C44: Michael Neipper | D44: Chocolate | E44: 905.25 | F44: =VLOOKUP(Relationships!D44,'Lookup Tables'!$A$4:$B$20,2,0) -> Candy | G44: =VLOOKUP(C44,'Lookup Tables'!$E$4:$K$11,7,0) -> North
A45: 1044 | B45: 8 | C45: Nancy Freehafer | D45: Chocolate | E45: 165.75 | F45: =VLOOKUP(Relationships!D45,'Lookup Tables'!$A$4:$B$20,2,0) -> Candy | G45: =VLOOKUP(C45,'Lookup Tables'!$E$4:$K$11,7,0) -> North
A46: 1045 | B46: 25 | C46: Laura Giussani | D46: Cajun Seasoning | E46: 2156 | F46: =VLOOKUP(Relationships!D46,'Lookup Tables'!$A$4:$B$20,2,0) -> Condiments | G46: =VLOOKUP(C46,'Lookup Tables'!$E$4:$K$11,7,0) -> East
A47: 1046 | B47: 26 | C47: Anne Larsen | D47: Boysenberry Spread | E47: 525 | F47: =VLOOKUP(Relationships!D47,'Lookup Tables'!$A$4:$B$20,2,0) -> Jams, Preserves | G47: =VLOOKUP(C47,'Lookup Tables'!$E$4:$K$11,7,0) -> South
A48: 1047 | B48: 29 | C48: Jan Kotas | D48: Coffee | E48: 1014 | F48: =VLOOKUP(Relationships!D48,'Lookup Tables'!$A$4:$B$20,2,0) -> Beverages | G48: =VLOOKUP(C48,'Lookup Tables'!$E$4:$K$11,7,0) -> West
A49: 1048 | B49: 6 | C49: Michael Neipper | D49: Dried Pears | E49: 2880 | F49: =VLOOKUP(Relationships!D49,'Lookup Tables'!$A$4:$B$20,2,0) -> Dried Fruit & Nuts | G49: =VLOOKUP(C49,'Lookup Tables'!$E$4:$K$11,7,0) -> North
... A341: 1432 | B341: 3 | C341: Mariya Sergienko | D341: Green Tea | E341: 71.76 | F341: =VLOOKUP(Relationships!D341,'Lookup Tables'!$A$4:$B$20,2,0) -> Beverages | G341: =VLOOKUP(C341,'Lookup Tables'!$E$4:$K$11,7,0) -> West

Sheet Lookup Tables
A1: Lookup Tables
A3: Product Name | B3: Category | E3: Salesperson | F3: City | G3: State | H3: Extension | I3: Manager | J3: Plan | K3: Region | N3: Customer ID | O3: Customer Name
A4: Wine | B4: Beverages | E4: Mariya Sergienko | F4: Las Vegas | G4: NV | H4: 5689 | I4: Kyla Walker | J4: Gold | K4: West | N4: 1 | O4: Tagchat
A5: Dried Plums | B5: Dried Fruit & Nuts | E5: Andrew Cencini | F5: New York | G5: NY | H5: 5674 | I5: Kyla Walker | J5: Platinum | K5: East | N5: 3 | O5: Centizu
A6: Dried Pears | B6: Dried Fruit & Nuts | E6: Nancy Freehafer | F6: Las Vegas | G6: NV | H6: 5612 | I6: Kyla Walker | J6: Gold | K6: North | N6: 4 | O6: Divanoodle
A7: Dried Apples | B7: Dried Fruit & Nuts | E7: Jan Kotas | F7: New York | G7: NY | H7: 5638 | I7: Grant Franklin | J7: Silver | K7: West | N7: 6 | O7: Layo
A8: Chai | B8: Beverages | E8: Michael Neipper | F8: Portland | G8: OR | H8: 5641 | I8: Celeste Dalton | J8: Platinum | K8: North | N8: 7 | O8: Cogilith
A9: Coffee | B9: Beverages | E9: Anne Larsen | F9: Portland | G9: OR | H9: 5675 | I9: Grant Franklin | J9: Silver | K9: South | N9: 8 | O9: Dabjam
A10: Chocolate Biscuits Mix | B10: Baked Goods & Mixes | E10: Laura Giussani | F10: Milwaukee | G10: WI | H10: 5688 | I10: Celeste Dalton | J10: Platinum | K10: East | N10: 9 | O10: Topicblab
A11: Chocolate | B11: Candy | E11: Robert Zare | F11: Los Angeles | G11: CA | H11: 5618 | I11: Celeste Dalton | J11: Gold | K11: West | N11: 10 | O11: Einti
A12: Clam Chowder | B12: Soups | N12: 11 | O12: Voonix
A13: Curry Sauce | B13: Sauces | N13: 12 | O13: Ooba
A14: Green Tea | B14: Beverages | N14: 25 | O14: Zoozzy
A15: Boysenberry Spread | B15: Jams, Preserves | N15: 26 | O15: Jabberstorm
A16: Cajun Seasoning | B16: Condiments | N16: 27 | O16: Devpulse
A17: Crab Meat | B17: Canned Meat | N17: 28 | O17: Thoughtbridge
A18: Ravioli | B18: Pasta | N18: 29 | O18: Fliptune
A19: Mozzarella | B19: Dairy Products
A20: Syrup | B20: Condiments
