Workbook
Name Slicer_Category: #N/A
Name Slicer_City: #N/A
Name Slicer_Payment_Method: #N/A
Name Slicer_Salesperson: #N/A

Sheet Insights
A2: Revenue by City
A3: Insight: Delhi generates the highest revenue among the three cities.
A4: Evidence: Delhi generates ₹67,700, Hyderabad generates ₹67,000, and Mumbai generates ₹62,900. Total revenue is ₹197,600.
A5: Business Meaning: Delhi is the leading city by revenue, but its revenue is only slightly higher than Hyderabad's. The company can study sales performance in both cities to identify opportunities for growth.
A7: Profit by City
A8: Insight: Delhi generates the highest profit among the three cities.
A9: Evidence: Delhi generates ₹24,200 in profit, while Hyderabad and Mumbai each generate ₹21,000. Total profit is ₹66,200.
A10: Business Meaning: Delhi is the most profitable city in the current analysis. The company can examine its sales and cost patterns to understand what contributes to its stronger profit.
A12: Revenue by Category
A13: Insight: Electronics is the largest contributor to total revenue.
A14: Evidence: Electronics generates ₹171,000, while Accessories generates ₹26,600. Total revenue is ₹197,600.
A15: Business Meaning: Electronics accounts for most of the company's revenue. The company should monitor demand and stock availability while exploring opportunities to improve Accessories sales.
... A42: Improve sales in Mumbai, maintain sufficient stock of popular products, continue supporting UPI payments, and identify ways to increase revenue and profit.

Sheet Dash Board

Sheet Pivot Table
A3: Row Labels | B3: Sum of Revenue | D3: Row Labels | E3: Sum of Profit | G3: Row Labels | H3: Sum of Revenue | J3: Row Labels | K3: Sum of Revenue
A4: Delhi | B4: 67700 | D4: Delhi | E4: 24200 | G4: Accessories | H4: 26600 | J4: Headset | K4: 27000
A5: Hyderabad | B5: 67000 | D5: Hyderabad | E5: 21000 | G5: Electronics | H5: 171000 | J5: Keyboard | K5: 9000
A6: Mumbai | B6: 62900 | D6: Mumbai | E6: 21000 | G6: Grand Total | H6: 197600 | J6: Laptop Stand | K6: 9600
A7: Grand Total | B7: 197600 | D7: Grand Total | E7: 66200 | J7: Monitor | K7: 108000
J8: Webcam | K8: 36000
J9: Wireless Mouse | K9: 8000
A10: Row Labels | B10: Sum of Revenue | D10: Row Labels | E10: Sum of Units | G10: Row Labels | H10: Sum of Revenue | J10: Grand Total | K10: 197600
A11: Aman | B11: 13600 | D11: Headset | E11: 9 | G11: Card | H11: 57100
A12: Neha | B12: 66200 | D12: Keyboard | E12: 6 | G12: Cash | H12: 10600
A13: Priya | B13: 56900 | D13: Laptop Stand | E13: 8 | G13: Unknown | H13: 18000
A14: Rahul | B14: 60900 | D14: Monitor | E14: 9 | G14: UPI | H14: 111900
A15: Grand Total | B15: 197600 | D15: Webcam | E15: 8 | G15: Grand Total | H15: 197600
D16: Wireless Mouse | E16: 10
D17: Grand Total | E17: 50

Sheet Raw Data
A1: Order ID | B1: Date | C1: Customer Name | D1: City | E1: Product Code | F1: Units | G1: Salesperson | H1: Payment Method | I1: Order Prefix | J1: Year Component | K1: Order Number | L1: Customer Label | M1: Product | N1: Category | O1: Unit Price | P1: Cost per Unit | Q1: Region | R1: Revenue | S1: Total Cost | T1: Profit | U1: Profit Margin | V1: Performance | W1: Transaction Review
A2: HYD25-001 | B2: 45662 | C2: Rahul Sharma | D2: Hyderabad | E2: P101 | F2: 2 | G2: Rahul | H2: UPI | I2: =LEFT(A2,3) -> HYD | J2: =MID(A2,4,2) -> 25 | K2: =RIGHT(A2,3) -> 001 | L2: =_xlfn.CONCAT(C2,"-",D2) -> Rahul Sharma-Hyderabad | M2: =_xlfn.XLOOKUP(Sales_Performance[[#This Row],[Product Code]],Table2[Product Code],Table2[Product]) -> Laptop Stand | N2: =VLOOKUP(Sales_Performance[[#This Row],[Product Code]],Table2[#All],3,0) -> Accessories | O2: =_xlfn.XLOOKUP(Sales_Performance[[#This Row],[Product Code]],Table2[Product Code],Table2[Unit Price]) -> 1200 | P2: =VLOOKUP(Sales_Performance[[#This Row],[Product Code]],Table2[],5,0) -> 800 | Q2: =VLOOKUP(D2,'City Lookup'!$A$3:$B$5,2,0) -> South | R2: =F2*O2 -> 2400 | S2: =F2*P2 -> 1600 | T2: =R2-S2 -> 800 | U2: =T2/R2*100% -> 0.33333333 | V2: =IF(AND(R2>=2000,S2>=500),"High Performance","Regular") -> High Performance | W2: =IF(OR(R2>=2000,T2>=500),"Rivew","Normal") -> Rivew
A3: MUM25-002 | B3: 45663 | C3: Priya Reddy | D3: Mumbai | E3: P102 | F3: 3 | G3: Priya | H3: Card | I3: =LEFT(A3,3) -> MUM | J3: =MID(A3,4,2) -> 25 | K3: =RIGHT(A3,3) -> 002 | L3: =_xlfn.CONCAT(C3,"-",D3) -> Priya Reddy-Mumbai | M3: =_xlfn.XLOOKUP(Sales_Performance[[#This Row],[Product Code]],Table2[Product Code],Table2[Product]) -> Wireless Mouse | N3: =VLOOKUP(Sales_Performance[[#This Row],[Product Code]],Table2[#All],3,0) -> Accessories | O3: =_xlfn.XLOOKUP(Sales_Performance[[#This Row],[Product Code]],Table2[Product Code],Table2[Unit Price]) -> 800 | P3: =VLOOKUP(Sales_Performance[[#This Row],[Product Code]],Table2[],5,0) -> 450 | Q3: =VLOOKUP(D3,'City Lookup'!$A$3:$B$5,2,0) -> West | R3: =F3*O3 -> 2400 | S3: =F3*P3 -> 1350 | T3: =R3-S3 -> 1050 | U3: =T3/R3*100% -> 0.4375 | V3: =IF(AND(R3>=2000,S3>=500),"High Performance","Regular") -> High Performance | W3: =IF(OR(R3>=2000,T3>=500),"Rivew","Normal") -> Rivew
A4: DEL25-003 | B4: 45664 | C4: Aman Khan | D4: Delhi | E4: P103 | F4: 1 | G4: Aman | H4: Cash | I4: =LEFT(A4,3) -> DEL | J4: =MID(A4,4,2) -> 25 | K4: =RIGHT(A4,3) -> 003 | L4: =_xlfn.CONCAT(C4,"-",D4) -> Aman Khan-Delhi | M4: =_xlfn.XLOOKUP(Sales_Performance[[#This Row],[Product Code]],Table2[Product Code],Table2[Product]) -> Keyboard | N4: =VLOOKUP(Sales_Performance[[#This Row],[Product Code]],Table2[#All],3,0) -> Accessories | O4: =_xlfn.XLOOKUP(Sales_Performance[[#This Row],[Product Code]],Table2[Product Code],Table2[Unit Price]) -> 1500 | P4: =VLOOKUP(Sales_Performance[[#This Row],[Product Code]],Table2[],5,0) -> 900 | Q4: =VLOOKUP(D4,'City Lookup'!$A$3:$B$5,2,0) -> North | R4: =F4*O4 -> 1500 | S4: =F4*P4 -> 900 | T4: =R4-S4 -> 600 | U4: =T4/R4*100% -> 0.4 | V4: =IF(AND(R4>=2000,S4>=500),"High Performance","Regular") -> Regular | W4: =IF(OR(R4>=2000,T4>=500),"Rivew","Normal") -> Rivew
A5: HYD25-004 | B5: 45665 | C5: Sneha Rao | D5: Hyderabad | E5: P104 | F5: 4 | G5: Rahul | H5: UPI | I5: =LEFT(A5,3) -> HYD | J5: =MID(A5,4,2) -> 25 | K5: =RIGHT(A5,3) -> 004 | L5: =_xlfn.CONCAT(C5,"-",D5) -> Sneha Rao-Hyderabad | M5: =_xlfn.XLOOKUP(Sales_Performance[[#This Row],[Product Code]],Table2[Product Code],Table2[Product]) -> Monitor | N5: =VLOOKUP(Sales_Performance[[#This Row],[Product Code]],Table2[#All],3,0) -> Electronics | O5: =_xlfn.XLOOKUP(Sales_Performance[[#This Row],[Product Code]],Table2[Product Code],Table2[Unit Price]) -> 12000 | P5: =VLOOKUP(Sales_Performance[[#This Row],[Product Code]],Table2[],5,0) -> 8500 | Q5: =VLOOKUP(D5,'City Lookup'!$A$3:$B$5,2,0) -> South | R5: =F5*O5 -> 48000 | S5: =F5*P5 -> 34000 | T5: =R5-S5 -> 14000 | U5: =T5/R5*100% -> 0.29166667 | V5: =IF(AND(R5>=2000,S5>=500),"High Performance","Regular") -> High Performance | W5: =IF(OR(R5>=2000,T5>=500),"Rivew","Normal") -> Rivew
A6: MUM25-005 | B6: 45666 | C6: Arjun Mehta | D6: Mumbai | E6: P101 | F6: 1 | G6: Priya | H6: Card | I6: =LEFT(A6,3) -> MUM | J6: =MID(A6,4,2) -> 25 | K6: =RIGHT(A6,3) -> 005 | L6: =_xlfn.CONCAT(C6,"-",D6) -> Arjun Mehta-Mumbai | M6: =_xlfn.XLOOKUP(Sales_Performance[[#This Row],[Product Code]],Table2[Product Code],Table2[Product]) -> Laptop Stand | N6: =VLOOKUP(Sales_Performance[[#This Row],[Product Code]],Table2[#All],3,0) -> Accessories | O6: =_xlfn.XLOOKUP(Sales_Performance[[#This Row],[Product Code]],Table2[Product Code],Table2[Unit Price]) -> 1200 | P6: =VLOOKUP(Sales_Performance[[#This Row],[Product Code]],Table2[],5,0) -> 800 | Q6: =VLOOKUP(D6,'City Lookup'!$A$3:$B$5,2,0) -> West | R6: =F6*O6 -> 1200 | S6: =F6*P6 -> 800 | T6: =R6-S6 -> 400 | U6: =T6/R6*100% -> 0.33333333 | V6: =IF(AND(R6>=2000,S6>=500),"High Performance","Regular") -> Regular | W6: =IF(OR(R6>=2000,T6>=500),"Rivew","Normal") -> Normal
A7: DEL25-006 | B7: 45667 | C7: Ayesha Ali | D7: Delhi | E7: P105 | F7: 5 | G7: Neha | H7: UPI | I7: =LEFT(A7,3) -> DEL | J7: =MID(A7,4,2) -> 25 | K7: =RIGHT(A7,3) -> 006 | L7: =_xlfn.CONCAT(C7,"-",D7) -> Ayesha Ali-Delhi | M7: =_xlfn.XLOOKUP(Sales_Performance[[#This Row],[Product Code]],Table2[Product Code],Table2[Product]) -> Headset | N7: =VLOOKUP(Sales_Performance[[#This Row],[Product Code]],Table2[#All],3,0) -> Electronics | O7: =_xlfn.XLOOKUP(Sales_Performance[[#This Row],[Product Code]],Table2[Product Code],Table2[Unit Price]) -> 3000 | P7: =VLOOKUP(Sales_Performance[[#This Row],[Product Code]],Table2[],5,0) -> 1800 | Q7: =VLOOKUP(D7,'City Lookup'!$A$3:$B$5,2,0) -> North | R7: =F7*O7 -> 15000 | S7: =F7*P7 -> 9000 | T7: =R7-S7 -> 6000 | U7: =T7/R7*100% -> 0.4 | V7: =IF(AND(R7>=2000,S7>=500),"High Performance","Regular") -> High Performance | W7: =IF(OR(R7>=2000,T7>=500),"Rivew","Normal") -> Rivew
A8: HYD25-007 | B8: 45668 | C8: Rohit Kumar | D8: Hyderabad | E8: P102 | F8: 2 | G8: Aman | H8: Cash | I8: =LEFT(A8,3) -> HYD | J8: =MID(A8,4,2) -> 25 | K8: =RIGHT(A8,3) -> 007 | L8: =_xlfn.CONCAT(C8,"-",D8) -> Rohit Kumar-Hyderabad | M8: =_xlfn.XLOOKUP(Sales_Performance[[#This Row],[Product Code]],Table2[Product Code],Table2[Product]) -> Wireless Mouse | N8: =VLOOKUP(Sales_Performance[[#This Row],[Product Code]],Table2[#All],3,0) -> Accessories | O8: =_xlfn.XLOOKUP(Sales_Performance[[#This Row],[Product Code]],Table2[Product Code],Table2[Unit Price]) -> 800 | P8: =VLOOKUP(Sales_Performance[[#This Row],[Product Code]],Table2[],5,0) -> 450 | Q8: =VLOOKUP(D8,'City Lookup'!$A$3:$B$5,2,0) -> South | R8: =F8*O8 -> 1600 | S8: =F8*P8 -> 900 | T8: =R8-S8 -> 700 | U8: =T8/R8*100% -> 0.4375 | V8: =IF(AND(R8>=2000,S8>=500),"High Performance","Regular") -> Regular | W8: =IF(OR(R8>=2000,T8>=500),"Rivew","Normal") -> Rivew
A9: MUM25-008 | B9: 45669 | C9: Neha Verma | D9: Mumbai | E9: P106 | F9: 3 | G9: Priya | H9: Card | I9: =LEFT(A9,3) -> MUM | J9: =MID(A9,4,2) -> 25 | K9: =RIGHT(A9,3) -> 008 | L9: =_xlfn.CONCAT(C9,"-",D9) -> Neha Verma-Mumbai | M9: =_xlfn.XLOOKUP(Sales_Performance[[#This Row],[Product Code]],Table2[Product Code],Table2[Product]) -> Webcam | N9: =VLOOKUP(Sales_Performance[[#This Row],[Product Code]],Table2[#All],3,0) -> Electronics | O9: =_xlfn.XLOOKUP(Sales_Performance[[#This Row],[Product Code]],Table2[Product Code],Table2[Unit Price]) -> 4500 | P9: =VLOOKUP(Sales_Performance[[#This Row],[Product Code]],Table2[],5,0) -> 2800 | Q9: =VLOOKUP(D9,'City Lookup'!$A$3:$B$5,2,0) -> West | R9: =F9*O9 -> 13500 | S9: =F9*P9 -> 8400 | T9: =R9-S9 -> 5100 | U9: =T9/R9*100% -> 0.37777778 | V9: =IF(AND(R9>=2000,S9>=500),"High Performance","Regular") -> High Performance | W9: =IF(OR(R9>=2000,T9>=500),"Rivew","Normal") -> Rivew
A10: DEL25-009 | B10: 45670 | C10: Kiran Rao | D10: Delhi | E10: P104 | F10: 2 | G10: Neha | H10: UPI | I10: =LEFT(A10,3) -> DEL | J10: =MID(A10,4,2) -> 25 | K10: =RIGHT(A10,3) -> 009 | L10: =_xlfn.CONCAT(C10,"-",D10) -> Kiran Rao-Delhi | M10: =_xlfn.XLOOKUP(Sales_Performance[[#This Row],[Product Code]],Table2[Product Code],Table2[Product]) -> Monitor | N10: =VLOOKUP(Sales_Performance[[#This Row],[Product Code]],Table2[#All],3,0) -> Electronics | O10: =_xlfn.XLOOKUP(Sales_Performance[[#This Row],[Product Code]],Table2[Product Code],Table2[Unit Price]) -> 12000 | P10: =VLOOKUP(Sales_Performance[[#This Row],[Product Code]],Table2[],5,0) -> 8500 | Q10: =VLOOKUP(D10,'City Lookup'!$A$3:$B$5,2,0) -> North | R10: =F10*O10 -> 24000 | S10: =F10*P10 -> 17000 | T10: =R10-S10 -> 7000 | U10: =T10/R10*100% -> 0.29166667 | V10: =IF(AND(R10>=2000,S10>=500),"High Performance","Regular") -> High Performance | W10: =IF(OR(R10>=2000,T10>=500),"Rivew","Normal") -> Rivew
A11: HYD25-010 | B11: 45671 | C11: Sana Khan | D11: Hyderabad | E11: P103 | F11: 3 | G11: Rahul | H11: Cash | I11: =LEFT(A11,3) -> HYD | J11: =MID(A11,4,2) -> 25 | K11: =RIGHT(A11,3) -> 010 | L11: =_xlfn.CONCAT(C11,"-",D11) -> Sana Khan-Hyderabad | M11: =_xlfn.XLOOKUP(Sales_Performance[[#This Row],[Product Code]],Table2[Product Code],Table2[Product]) -> Keyboard | N11: =VLOOKUP(Sales_Performance[[#This Row],[Product Code]],Table2[#All],3,0) -> Accessories | O11: =_xlfn.XLOOKUP(Sales_Performance[[#This Row],[Product Code]],Table2[Product Code],Table2[Unit Price]) -> 1500 | P11: =VLOOKUP(Sales_Performance[[#This Row],[Product Code]],Table2[],5,0) -> 900 | Q11: =VLOOKUP(D11,'City Lookup'!$A$3:$B$5,2,0) -> South | R11: =F11*O11 -> 4500 | S11: =F11*P11 -> 2700 | T11: =R11-S11 -> 1800 | U11: =T11/R11*100% -> 0.4 | V11: =IF(AND(R11>=2000,S11>=500),"High Performance","Regular") -> High Performance | W11: =IF(OR(R11>=2000,T11>=500),"Rivew","Normal") -> Rivew
A12: MUM25-011 | B12: 45672 | C12: Vivek Patel | D12: Mumbai | E12: P105 | F12: 2 | G12: Aman | H12: UPI | I12: =LEFT(A12,3) -> MUM | J12: =MID(A12,4,2) -> 25 | K12: =RIGHT(A12,3) -> 011 | L12: =_xlfn.CONCAT(C12,"-",D12) -> Vivek Patel-Mumbai | M12: =_xlfn.XLOOKUP(Sales_Performance[[#This Row],[Product Code]],Table2[Product Code],Table2[Product]) -> Headset | N12: =VLOOKUP(Sales_Performance[[#This Row],[Product Code]],Table2[#All],3,0) -> Electronics | O12: =_xlfn.XLOOKUP(Sales_Performance[[#This Row],[Product Code]],Table2[Product Code],Table2[Unit Price]) -> 3000 | P12: =VLOOKUP(Sales_Performance[[#This Row],[Product Code]],Table2[],5,0) -> 1800 | Q12: =VLOOKUP(D12,'City Lookup'!$A$3:$B$5,2,0) -> West | R12: =F12*O12 -> 6000 | S12: =F12*P12 -> 3600 | T12: =R12-S12 -> 2400 | U12: =T12/R12*100% -> 0.4 | V12: =IF(AND(R12>=2000,S12>=500),"High Performance","Regular") -> High Performance | W12: =IF(OR(R12>=2000,T12>=500),"Rivew","Normal") -> Rivew
A13: DEL25-012 | B13: 45673 | C13: Meera Singh | D13: Delhi | E13: P106 | F13: 4 | G13: Neha | H13: Unknown | I13: =LEFT(A13,3) -> DEL | J13: =MID(A13,4,2) -> 25 | K13: =RIGHT(A13,3) -> 012 | L13: =_xlfn.CONCAT(C13,"-",D13) -> Meera Singh-Delhi | M13: =_xlfn.XLOOKUP(Sales_Performance[[#This Row],[Product Code]],Table2[Product Code],Table2[Product]) -> Webcam | N13: =VLOOKUP(Sales_Performance[[#This Row],[Product Code]],Table2[#All],3,0) -> Electronics | O13: =_xlfn.XLOOKUP(Sales_Performance[[#This Row],[Product Code]],Table2[Product Code],Table2[Unit Price]) -> 4500 | P13: =VLOOKUP(Sales_Performance[[#This Row],[Product Code]],Table2[],5,0) -> 2800 | Q13: =VLOOKUP(D13,'City Lookup'!$A$3:$B$5,2,0) -> North | R13: =F13*O13 -> 18000 | S13: =F13*P13 -> 11200 | T13: =R13-S13 -> 6800 | U13: =T13/R13*100% -> 0.37777778 | V13: =IF(AND(R13>=2000,S13>=500),"High Performance","Regular") -> High Performance | W13: =IF(OR(R13>=2000,T13>=500),"Rivew","Normal") -> Rivew
... A21: MUM25-020 | B21: 45681 | C21: Priya Reddy | D21: Mumbai | E21: P102 | F21: 1 | G21: Priya | H21: Card | I21: =LEFT(A21,3) -> MUM | J21: =MID(A21,4,2) -> 25 | K21: =RIGHT(A21,3) -> 020 | L21: =_xlfn.CONCAT(C21,"-",D21) -> Priya Reddy-Mumbai | M21: =_xlfn.XLOOKUP(Sales_Performance[[#This Row],[Product Code]],Table2[Product Code],Table2[Product]) -> Wireless Mouse | N21: =VLOOKUP(Sales_Performance[[#This Row],[Product Code]],Table2[#All],3,0) -> Accessories | O21: =_xlfn.XLOOKUP(Sales_Performance[[#This Row],[Product Code]],Table2[Product Code],Table2[Unit Price]) -> 800 | P21: =VLOOKUP(Sales_Performance[[#This Row],[Product Code]],Table2[],5,0) -> 450 | Q21: =VLOOKUP(D21,'City Lookup'!$A$3:$B$5,2,0) -> West | R21: =F21*O21 -> 800 | S21: =F21*P21 -> 450 | T21: =R21-S21 -> 350 | U21: =T21/R21*100% -> 0.4375 | V21: =IF(AND(R21>=2000,S21>=500),"High Performance","Regular") -> Regular | W21: =IF(OR(R21>=2000,T21>=500),"Rivew","Normal") -> Normal

Sheet Product Lookup
A1: Product Code | B1: Product | C1: Category | D1: Unit Price | E1: Cost Per Unit
A2: P101 | B2: Laptop Stand | C2: Accessories | D2: 1200 | E2: 800
A3: P102 | B3: Wireless Mouse | C3: Accessories | D3: 800 | E3: 450
A4: P103 | B4: Keyboard | C4: Accessories | D4: 1500 | E4: 900
A5: P104 | B5: Monitor | C5: Electronics | D5: 12000 | E5: 8500
A6: P105 | B6: Headset | C6: Electronics | D6: 3000 | E6: 1800
A7: P106 | B7: Webcam | C7: Electronics | D7: 4500 | E7: 2800

Sheet City Lookup
A1: Column1 | B1: Column2
A2: City | B2: Region
A3: Hyderabad | B3: South
A4: Mumbai | B4: West
A5: Delhi | B5: North
